Workbook

Sheet Cover
A1: MONTEC
A2: Financial Model — 13-SKU Edition (AMD)
A4: Quiet-luxury leather accessories · Batch 001 · Armenia & the Armenian diaspora
A5: Rebuilt 2026-08-02 · Base case · AMD
A7: Why this version exists
A8: The original model priced 6 generic products in USD ($95–$650). This version re-keys the same methodology (unit economics → revenue build → P&L → cash flow → break-even) against the 13 locked Batch 001 SKUs, priced in AMD, per montec/CLAUDE.md.
A10: Contents
A11: Assumptions | B11: FX rate, startup capital, opex, corporate-channel status
A12: Unit Economics | B12: Price, modeled COGS and gross margin per SKU (13 rows, 5 TBD)
A13: Startup Capital | B13: How the launch budget is allocated
A14: Revenue Build | B14: Year 1 monthly revenue — DTC base case, corporate paused
A15: P&L 3-Year | B15: Three-year profit & loss
A16: Cash Flow Y1 | B16: Monthly cash — proves the runway never goes negative
A17: Break-even & Scenarios | B17: Break-even, conservative/base/upside, corporate-resumption memo
A19: Colour legend
A20: Blue fill | B20: Hardcoded input / scenario lever — edit these
A21: Black text | B21: Formula — do not overwrite
A22: Green text | B22: Links to another sheet
A23: Yellow fill | B23: Key assumption to sanity-check
A25: ⚠ Corporate channel status
A26: The Nairi Insurance 500-unit personalized card-holder programme (the corporate anchor in the original Business Plan / GTM Strategy) is REAL but currently PAUSED — Nairi is going through internal restructuring and every project on their side is on hold as of 2026-08-02. This model's Year-1 base case therefore assumes ZERO corporate revenue. See the Break-even & Scenarios sheet for what changes if/when it resumes.

Sheet Assumptions
A1: Assumptions
A2: Blue = input you can change · Yellow = key assumption to sanity-check
A4: CURRENCY
A5: FX rate (AMD per USD) | B5: 400 | C5: Approximate — confirm current rate before relying on USD-equivalents anywhere
A7: CAPITAL
A8: Startup capital (USD) | B8: 5000
A9: Startup capital (AMD) | B9: =B8*B5
A11: CORPORATE CHANNEL — NAIRI INSURANCE (500-unit programme)
A12: Status | B12: PAUSED (Nairi internal restructuring, confirmed 2026-08-02)
A13: Active in Year-1 base case? (1=yes, 0=no) | B13: 0
A14: If resumed — corporate bulk unit price, THE ACCESS (AMD) | B14: 17500 | C14: Modeled at ~58% of retail 30,000 AMD, mirroring the original $55/$95 ratio — not a confirmed quote
A15: If resumed — programme size (units) | B15: 500
A17: DTC — YEAR 1 MONTHLY UNIT RAMP (blended across priced SKUs)
A18: Month | B18: M1 | C18: M2 | D18: M3 | E18: M4 | F18: M5 | G18: M6 | H18: M7 | I18: M8 | J18: M9 | K18: M10 | L18: M11 | M18: M12
A19: DTC units | B19: 4 | C19: 5 | D19: 6 | E19: 8 | F19: 9 | G19: 10 | H19: 11 | I19: 12 | J19: 13 | K19: 14 | L19: 15 | M19: 16
A21: DTC blended average price (AMD) — sales-mix weighted, see Unit Economics
A22: Blended DTC price per unit | B22: 82000 | C22: Weighted toward accessible SKUs early (Access/Vision/Capital/Arena/Voyager) with some Closer/Executive/Founder mix — see notes in Unit Economics. Recompute once real sales-mix data exists.
A23: Blended DTC COGS ratio (modeled) | B23: 0.3 | C23: Flat ~70% GM assumption carried over from the original model — confirm real cost breakdown with Artem/Levon
A25: OPERATING EXPENSES (annual unless noted, AMD)
A26: Item | B26: Year 1 | C26: Year 2 | D26: Year 3
A27: Marketing & content (incl. launch) | B27: =3000*$B$5 | C27: =4000*$B$5 | D27: =6000*$B$5
A28: Shipping & fulfilment | B28: =1400*$B$5 | C28: =2600*$B$5 | D28: =4200*$B$5
A29: Software & store (Shopify, domain) | B29: =360*$B$5 | C29: =420*$B$5 | D29: =480*$B$5
A30: Personalization / engraving | B30: =400*$B$5 | C30: =900*$B$5 | D30: =1500*$B$5
A31: Misc & admin | B31: =600*$B$5 | C31: =900*$B$5 | D31: =1200*$B$5
A32: Payment processing (% of DTC revenue) | B32: 0.03 | C32: 0.03 | D32: 0.03
A34: ONE-TIME SETUP (Month 1, non-COGS, AMD)
A35: Online store build & first-year plan | B35: =500*$B$5
A36: Corporate sample & pitch kit | B36: =500*$B$5
A37: Engraving setup / tooling | B37: =300*$B$5
A38: Content production kit | B38: =400*$B$5
A39: Total one-time setup | B39: =SUM(B35:B38)

Sheet Unit Economics
A1: Unit Economics
A2: Price, modeled COGS and gross margin per product — all 13 locked Batch 001 SKUs
A4: SKU | B4: Type | C4: Price (AMD) | D4: Modeled COGS (AMD) | E4: Gross Profit (AMD) | F4: GM % | G4: Status
A5: THE FOUNDER | B5: Weekender | C5: 270000 | D5: =C5*Assumptions!$B$23 | E5: =C5-D5 | F5: =E5/C5 | G5: Confirmed price
A6: THE EXECUTIVE | B6: Briefcase | C6: 230000 | D6: =C6*Assumptions!$B$23 | E6: =C6-D6 | F6: =E6/C6 | G6: Confirmed price
A7: THE UNIT | B7: Laptop module | C7: TBD | D7: — | E7: — | F7: — | G7: Price not yet confirmed — excluded from revenue math, do not invent
A8: THE CLOSER | B8: Messenger bag | C8: 190000 | D8: =C8*Assumptions!$B$23 | E8: =C8-D8 | F8: =E8/C8 | G8: Confirmed price
A9: THE ARENA | B9: Desk mat | C9: 40000 | D9: =C9*Assumptions!$B$23 | E9: =C9-D9 | F9: =E9/C9 | G9: Confirmed price
A10: THE BRIEF | B10: Men's clutch | C10: TBD | D10: — | E10: — | F10: — | G10: Price not yet confirmed — excluded from revenue math, do not invent
A11: THE CAPITAL | B11: Bifold wallet | C11: 40000 | D11: =C11*Assumptions!$B$23 | E11: =C11-D11 | F11: =E11/C11 | G11: Confirmed price
A12: THE TREASURY | B12: Long wallet | C12: TBD | D12: — | E12: — | F12: — | G12: Price not yet confirmed — excluded from revenue math, do not invent
A13: THE ACCESS | B13: Cardholder | C13: 30000 | D13: =C13*Assumptions!$B$23 | E13: =C13-D13 | F13: =E13/C13 | G13: Confirmed price
A14: THE VOYAGER | B14: Dopp kit | C14: 40000 | D14: =C14*Assumptions!$B$23 | E14: =C14-D14 | F14: =E14/C14 | G14: Confirmed price
A15: THE VISION | B15: Glasses case | C15: 30000 | D15: =C15*Assumptions!$B$23 | E15: =C15-D15 | F15: =E15/C15 | G15: Confirmed price
A16: THE BACKBONE | B16: Brown belt | C16: TBD | D16: — | E16: — | F16: — | G16: Price not yet confirmed — excluded from revenue math, do not invent
A17: THE STANDARD | B17: Black belt | C17: TBD | D17: — | E17: — | F17: — | G17: Price not yet confirmed — excluded from revenue math, do not invent
A19: Corporate gift edition — THE ACCESS (bulk) | C19: =Assumptions!B14 | D19: =C19*Assumptions!$B$23 | E19: =C19-D19 | F19: =E19/C19 | G19: Modeled — see Assumptions
A21: Notes
A22: Material = Italian full-grain vegetable-tanned calfskin + Italian brass hardware, per montec/CLAUDE.md. Modeled COGS uses a flat 30% ratio (~70% GM) carried over from the original 6-product model's observed range (68.3–73.1%) — this is a planning estimate, not a confirmed cost breakdown from Artem/Levon. Recompute once real per-piece costs are known. The 5 TBD-price SKUs (Unit, Brief, Treasury, Backbone, Standard) are excluded from Revenue Build until the user provides real AMD prices.

Sheet Startup Capital
A1: Startup Capital
A2: Allocation of the launch budget — 5000 USD / see Assumptions!B9 for AMD
A4: Use of funds | B4: Amount (AMD) | C4: % of total | D4: Purpose
A5: Initial materials & hardware | B5: =Assumptions!$B$9*C5 | C5: 0.12 | D5: Hides, brass, linings, thread for first batches
A6: Branded packaging (first run) | B6: =Assumptions!$B$9*C6 | C6: 0.14 | D6: Boxes, dust bags, cards — the unboxing must feel luxury
A7: Corporate sample & pitch kit | B7: =Assumptions!$B$9*C7 | C7: 0.1 | D7: One flawless sample — held ready for when Nairi (or another corporate lead) resumes
A8: Content production kit | B8: =Assumptions!$B$9*C8 | C8: 0.08 | D8: Props and minor gear for cinematic reels
A9: Online store (Shopify + domain, 1yr) | B9: =Assumptions!$B$9*C9 | C9: 0.1 | D9: Application-based storefront
A10: Launch marketing | B10: =Assumptions!$B$9*C10 | C10: 0.3 | D10: Seed reach for the zero-follower launch phase
A11: Personalization / engraving setup | B11: =Assumptions!$B$9*C11 | C11: 0.06 | D11: Laser engraving of initials for corporate & monogram
A12: Working-capital contingency | B12: =Assumptions!$B$9*C12 | C12: 0.1 | D12: Buffer for timing and the unexpected
A13: Total allocated | B13: =SUM(B5:B12) | C13: =SUM(C5:C12)

Sheet Revenue Build
A1: Revenue Build — Year 1
A2: Monthly units and revenue by channel, AMD — corporate channel PAUSED in this base case
A4: Line item | B4: M1 | C4: M2 | D4: M3 | E4: M4 | F4: M5 | G4: M6 | H4: M7 | I4: M8 | J4: M9 | K4: M10 | L4: M11 | M4: M12 | N4: Year 1
A5: DTC — units | B5: =Assumptions!B19 | C5: =Assumptions!C19 | D5: =Assumptions!D19 | E5: =Assumptions!E19 | F5: =Assumptions!F19 | G5: =Assumptions!G19 | H5: =Assumptions!H19 | I5: =Assumptions!I19 | ... M5: =Assumptions!M19 | N5: =SUM(B5:M5)
A6: DTC — revenue | B6: =B5*Assumptions!$B$22 | C6: =C5*Assumptions!$B$22 | D6: =D5*Assumptions!$B$22 | E6: =E5*Assumptions!$B$22 | F6: =F5*Assumptions!$B$22 | G6: =G5*Assumptions!$B$22 | H6: =H5*Assumptions!$B$22 | I6: =I5*Assumptions!$B$22 | ... M6: =M5*Assumptions!$B$22 | N6: =SUM(B6:M6)
A7: Corporate — units (0 while paused) | B7: 0 | C7: 0 | D7: 0 | E7: 0 | F7: 0 | G7: 0 | H7: 0 | I7: 0 | J7: 0 | K7: 0 | L7: 0 | M7: 0 | N7: =SUM(B7:M7)
A8: Corporate — revenue | B8: =B7*Assumptions!$B$14 | C8: =C7*Assumptions!$B$14 | D8: =D7*Assumptions!$B$14 | E8: =E7*Assumptions!$B$14 | F8: =F7*Assumptions!$B$14 | G8: =G7*Assumptions!$B$14 | H8: =H7*Assumptions!$B$14 | I8: =I7*Assumptions!$B$14 | ... M8: =M7*Assumptions!$B$14 | N8: =SUM(B8:M8)
A9: Total revenue | B9: =B6+B8 | C9: =C6+C8 | D9: =D6+D8 | E9: =E6+E8 | F9: =F6+F8 | G9: =G6+G8 | H9: =H6+H8 | I9: =I6+I8 | ... M9: =M6+M8 | N9: =SUM(B9:M9)
A11: Comment
A12: Corporate row is zeroed because the Nairi Insurance 500-unit programme is paused pending their internal restructuring (confirmed 2026-08-02) — this is a real relationship, not a cancelled one, so re-activate the Corporate — units row the moment it resumes. DTC ramps on the same monthly shape as the original model; all monthly unit cells are blue inputs.

Sheet P&L 3-Year
A1: Profit & Loss — Three Year (AMD)
A2: Year 1 pulls from Revenue Build (corporate paused); Years 2-3 scale DTC only unless corporate resumes — see Break-even & Scenarios
B4: Year 1 | C4: Year 2 | D4: Year 3
A5: DTC revenue | B5: ='Revenue Build'!N6 | C5: =B5*2.9 | D5: =B5*5.7
A6: Corporate revenue (0 while paused) | B6: ='Revenue Build'!N8 | C6: 0 | D6: 0
A7: Total revenue | B7: =B5+B6 | C7: =C5+C6 | D7: =D5+D6
A8: Total COGS (modeled @ blended ratio) | B8: =B7*Assumptions!$B$23 | C8: =C7*Assumptions!$B$23 | D8: =D7*Assumptions!$B$23
A9: Gross profit | B9: =B7-B8 | C9: =C7-C8 | D9: =D7-D8
A10: Gross margin % | B10: =B9/B7 | C10: =C9/C7 | D10: =D9/D7
A12: Operating expenses
A13: Marketing & content (incl. launch) | B13: =Assumptions!B27 | C13: =Assumptions!C27 | D13: =Assumptions!D27
A14: Shipping & fulfilment | B14: =Assumptions!B28 | C14: =Assumptions!C28 | D14: =Assumptions!D28
A15: Software & store (Shopify, domain) | B15: =Assumptions!B29 | C15: =Assumptions!C29 | D15: =Assumptions!D29
A16: Personalization / engraving | B16: =Assumptions!B30 | C16: =Assumptions!C30 | D16: =Assumptions!D30
A17: Misc & admin | B17: =Assumptions!B31 | C17: =Assumptions!C31 | D17: =Assumptions!D31
A18: Payment processing | B18: =B5*Assumptions!$B$32 | C18: =C5*Assumptions!$B$32 | D18: =D5*Assumptions!$B$32
A19: Total operating expenses | B19: =SUM(B13:B18) | C19: =SUM(C13:C18) | D19: =SUM(D13:D18)
A20: Operating profit (EBITDA) | B20: =B9-B19 | C20: =C9-C19 | D20: =D9-D19
A21: Operating margin % | B21: =B20/B7 | C21: =C20/C7 | D21: =D20/D7
A23: Note: with the corporate channel paused, Year-1 operating profit is materially smaller than the original model (which leaned on corporate for ~58% of Year-1 revenue). This is the honest DTC-only base case. See Break-even & Scenarios for the corporate-resumption upside.

Sheet Cash Flow Y1
A1: Cash Flow — Year 1 (monthly, AMD)
A2: Opening = Assumptions!B9 · shows whether the runway ever goes negative with corporate paused
A4: Line item | B4: M1 | C4: M2 | D4: M3 | E4: M4 | F4: M5 | G4: M6 | H4: M7 | I4: M8 | J4: M9 | K4: M10 | L4: M11 | M4: M12 | N4: Year 1
A5: Revenue collected | B5: ='Revenue Build'!B9 | C5: ='Revenue Build'!C9 | D5: ='Revenue Build'!D9 | E5: ='Revenue Build'!E9 | F5: ='Revenue Build'!F9 | G5: ='Revenue Build'!G9 | H5: ='Revenue Build'!H9 | I5: ='Revenue Build'!I9 | ... M5: ='Revenue Build'!M9 | N5: =SUM(B5:M5)
A6: less: COGS (cash) | B6: =-B5*Assumptions!$B$23 | C6: =-C5*Assumptions!$B$23 | D6: =-D5*Assumptions!$B$23 | E6: =-E5*Assumptions!$B$23 | F6: =-F5*Assumptions!$B$23 | G6: =-G5*Assumptions!$B$23 | H6: =-H5*Assumptions!$B$23 | I6: =-I5*Assumptions!$B$23 | ... M6: =-M5*Assumptions!$B$23 | N6: =SUM(B6:M6)
A7: less: operating expenses (spread evenly) | B7: =-'P&L 3-Year'!$B$19/12 | C7: =-'P&L 3-Year'!$B$19/12 | D7: =-'P&L 3-Year'!$B$19/12 | E7: =-'P&L 3-Year'!$B$19/12 | F7: =-'P&L 3-Year'!$B$19/12 | G7: =-'P&L 3-Year'!$B$19/12 | H7: =-'P&L 3-Year'!$B$19/12 | I7: =-'P&L 3-Year'!$B$19/12 | ... M7: =-'P&L 3-Year'!$B$19/12 | N7: =SUM(B7:M7)
A8: less: one-time setup (M1) | B8: =-Assumptions!B39 | C8: 0 | D8: 0 | E8: 0 | F8: 0 | G8: 0 | H8: 0 | I8: 0 | J8: 0 | K8: 0 | L8: 0 | M8: 0 | N8: =SUM(B8:M8)
A9: Net cash flow | B9: =SUM(B5:B8) | C9: =SUM(C5:C8) | D9: =SUM(D5:D8) | E9: =SUM(E5:E8) | F9: =SUM(F5:F8) | G9: =SUM(G5:G8) | H9: =SUM(H5:H8) | I9: =SUM(I5:I8) | ... M9: =SUM(M5:M8) | N9: =SUM(B9:M9)
A10: Opening cash | B10: =Assumptions!B9 | C10: =B11 | D10: =C11 | E10: =D11 | F10: =E11 | G10: =F11 | H10: =G11 | I10: =H11 | J10: =I11 | ... M10: =L11
A11: Closing cash | B11: =B10+B9 | C11: =C10+C9 | D11: =D10+D9 | E11: =E10+E9 | F11: =F10+F9 | G11: =G10+G9 | H11: =H10+H9 | I11: =I10+I9 | ... M11: =M10+M9
A13: Minimum closing cash (Y1) | B13: =MIN(B11:M11)

Sheet Break-even & Scenarios
A1: Break-even & Scenarios
A2: What it takes to cover costs, and the corporate-resumption upside
A4: BREAK-EVEN (year 1 basis, DTC-only base case)
A5: Annual fixed operating expenses | B5: ='P&L 3-Year'!B19
A6: Blended gross margin % | B6: ='P&L 3-Year'!B9/'P&L 3-Year'!B7
A7: Break-even revenue (annual) | B7: =B5/B6
A8: Projected Year-1 revenue (DTC-only base case) | B8: ='P&L 3-Year'!B7
A9: Revenue cushion above break-even | B9: =B8-B7
A11: SCENARIOS (year 1, DTC-only base case)
A12: Metric | B12: Conservative | C12: Base | D12: Upside
A13: Revenue vs base (lever) | B13: 0.6 | C13: 1 | D13: 1.5
A14: Total revenue | B14: ='P&L 3-Year'!$B$7*B13 | C14: ='P&L 3-Year'!$B$7*C13 | D14: ='P&L 3-Year'!$B$7*D13
A15: Operating profit (approx., same opex) | B15: =B14*B6-B5 | C15: =C14*B6-B5 | D15: =D14*B6-B5
A17: ⚠ CORPORATE-RESUMPTION MEMO (Nairi Insurance, currently paused)
A18: If the 500-unit programme resumes at the modeled bulk price:
A19: Additional revenue (500 units) | B19: =Assumptions!B15*Assumptions!B14
A20: Additional gross profit (@ modeled corporate GM%) | B20: ='Unit Economics'!E19*Assumptions!B15
A22: This scenario is a memo, not a forecast — do not present the corporate-resumption figures as committed revenue anywhere external until Nairi actually restarts the programme.
